baiji/__init__.py
baiji/cached_file.py
baiji/cli.py
baiji/config.py
baiji/connection.py
baiji/copy.py
baiji/exceptions.py
baiji/package_version.py
baiji/path.py
baiji/s3.py
baiji/test_config.py
baiji/test_s3.py
baiji/test_s3_cached_file.py
baiji/test_s3_path.py
baiji/test_s3_sync.py
baiji/test_s3_tempdir.py
baiji/util/__init__.py
baiji/util/console.py
baiji/util/environ.py
baiji/util/lookup.py
baiji/util/md5.py
baiji/util/munging.py
baiji/util/parallel.py
baiji/util/reachability.py
baiji/util/shutillib.py
baiji/util/tempfile.py
baiji/util/test_environ.py
baiji/util/test_md5.py
baiji/util/test_reachability.py
baiji/util/test_support.py
baiji/util/test_tempfile.py
baiji/util/with_progressbar.py
baiji/util/yaml.py
metabaiji-2.12.2.data/scripts/s3
metabaiji-2.12.2.dist-info/LICENSE
metabaiji-2.12.2.dist-info/METADATA
metabaiji-2.12.2.dist-info/WHEEL
metabaiji-2.12.2.dist-info/top_level.txt
metabaiji-2.12.2.dist-info/RECORD
