Metadata-Version: 2.1
Name: metabaiji
Version: 2.12.2
Summary: High-level Python abstraction layer for Amazon S3
Home-page: https://github.com/metabolize/baiji
Author: Body Labs
Author-email: github@paulmelnikow.com
License: MIT
Platform: UNKNOWN
Classifier: Development Status :: 4 - Beta
Classifier: Intended Audience :: Developers
Classifier: License :: OSI Approved :: Apache Software License
Classifier: Operating System :: OS Independent
Classifier: Programming Language :: Python :: 2.7
Classifier: Programming Language :: Python :: 3
Requires-Dist: boto (<3,>=2.38.0)
Requires-Dist: pyyaml (<6,>=5.3.1)
Requires-Dist: requests (<3,>=2.9.1)
Requires-Dist: plumbum (<2,>=1.6.2)
Requires-Dist: pyspin (<2,>=1.1.1)
Requires-Dist: six
